README.txt
setup.cfg
setup.py
docs/HISTORY.txt
docs/INSTALL.txt
docs/LICENSE.GPL
docs/LICENSE.txt
iccommunity/__init__.py
iccommunity.mailman.egg-info/PKG-INFO
iccommunity.mailman.egg-info/SOURCES.txt
iccommunity.mailman.egg-info/dependency_links.txt
iccommunity.mailman.egg-info/entry_points.txt
iccommunity.mailman.egg-info/namespace_packages.txt
iccommunity.mailman.egg-info/not-zip-safe
iccommunity.mailman.egg-info/requires.txt
iccommunity.mailman.egg-info/top_level.txt
iccommunity/mailman/README.txt
iccommunity/mailman/__init__.py
iccommunity/mailman/browser.txt
iccommunity/mailman/config.py
iccommunity/mailman/configure.zcml
iccommunity/mailman/generate_docs.sh
iccommunity/mailman/i18n.py
iccommunity/mailman/interfaces.py
iccommunity/mailman/mailman.py
iccommunity/mailman/preferences.py
iccommunity/mailman/setuphandlers.py
iccommunity/mailman/version.txt
iccommunity/mailman/vocabularies.py
iccommunity/mailman/vocabularies.zcml
iccommunity/mailman/Extensions/__init__.py
iccommunity/mailman/Extensions/install.py
iccommunity/mailman/browser/__init__.py
iccommunity/mailman/browser/admin.py
iccommunity/mailman/browser/admin.zcml
iccommunity/mailman/browser/configure.zcml
iccommunity/mailman/profiles/default/import_steps.xml
iccommunity/mailman/profiles/default/memberdata_properties.xml
iccommunity/mailman/tests/__init__.py
iccommunity/mailman/tests/base.py
iccommunity/mailman/tests/test_configlets.py
iccommunity/mailman/tests/test_configlets.txt
iccommunity/mailman/tests/test_mailmanplone.py
iccommunity/mailman/tests/test_user_subscribed_lists.txt
iccommunity/mailman/tests/test_utilities.py
iccommunity/mailman/tests/test_utilities.txt
iccommunity/mailman/tests/utils.py
iccommunity/mailman/tests/samples/mailman/__init__.py
iccommunity/mailman/tests/samples/mailman/Mailman/Utils.py
iccommunity/mailman/tests/samples/mailman/Mailman/__init__.py