Metadata-Version: 1.0
Name: iccommunity.mailman
Version: 1.0-dev-r371
Summary: icSemantic.Mailman
Home-page: http://www.platecom.com/productos/iccommunity.mailman/
Author: Inter-Cultura Consultora SRL - Ibai Sistemas SA - Eusko Ikaskuntza-Sociedad de Estudios Vascos
Author-email: dev@inter-cultura.com
License: GPL
Keywords: iccommunity,platecom,community,mailman,plone
Platform: UNKNOWN
Classifier: Topic :: Communications :: Email :: Mailing List Servers
Classifier: Environment :: Web Environment
Classifier: Framework :: Plone
Classifier: Development Status :: 4 - Beta
Classifier: Intended Audience :: Information Technology
Classifier: License :: OSI Approved :: GNU General Public License (GPL)
Classifier: Operating System :: OS Independent
Classifier: Programming Language :: Python
